{
    "id": 1353,
    "title": "芋頭排骨粥[健康初春食譜]",
    "description": "",
    "detailsUrl": "http://pic.daydaycook.com/production/videos/20160619_2/1353.mp4",
    "indexUrl": null,
    "imageUrl": "http://pic.daydaycook.com/production/ImageMigration/1000x750/recipe_1353_1684.jpg",
    "clickCount": 805,
    "shareCount": 0,
    "maketime": "30分鐘",
    "releaseDate": "2013-02-26 00:00:00.0",
    "ingredientImageUrl": null,
    "ingredientImageUrl2": null,
    "ingredientImageUrl3": null,
    "ingredients": [
        {
            "name": "水",
            "cnt": "2000",
            "unit": "毫升",
            "type": "0",
            "typeName": null
        },
        {
            "name": "薑",
            "cnt": "10",
            "unit": "克",
            "type": "0",
            "typeName": null
        },
        {
            "name": "鹽 ",
            "cnt": "10",
            "unit": "克",
            "type": "0",
            "typeName": null
        },
        {
            "name": "白胡椒粉",
            "cnt": "4",
            "unit": "克",
            "type": "0",
            "typeName": null
        },
        {
            "name": "米",
            "cnt": "150",
            "unit": "克",
            "type": "0",
            "typeName": null
        },
        {
            "name": "蔥",
            "cnt": "10",
            "unit": "克",
            "type": "0",
            "typeName": null
        },
        {
            "name": "排骨",
            "cnt": "250",
            "unit": "克",
            "type": "0",
            "typeName": null
        },
        {
            "name": "芋頭",
            "cnt": "200",
            "unit": "克",
            "type": "0",
            "typeName": null
        },
        {
            "name": "雞精",
            "cnt": "",
            "unit": "適量",
            "type": "0",
            "typeName": null
        }
    ],
    "steps": [
        {
            "stepNo": 1,
            "content": "材料",
            "imageUrl": "http://pic.daydaycook.com/production/ImageMigration/384x288/recipe_content_5632_item_0.jpg",
            "languageId": null
        },
        {
            "stepNo": 2,
            "content": "芋頭切成小方塊",
            "imageUrl": "http://pic.daydaycook.com/production/ImageMigration/384x288/recipe_content_5632_item_1.jpg",
            "languageId": null
        },
        {
            "stepNo": 3,
            "content": "香蔥切碎",
            "imageUrl": "http://pic.daydaycook.com/production/ImageMigration/384x288/recipe_content_5633_item_0.jpg",
            "languageId": null
        },
        {
            "stepNo": 4,
            "content": "姜切片",
            "imageUrl": "http://pic.daydaycook.com/production/ImageMigration/384x288/recipe_content_5633_item_1.jpg",
            "languageId": null
        },
        {
            "stepNo": 5,
            "content": "白米洗淨",
            "imageUrl": "http://pic.daydaycook.com/production/ImageMigration/384x288/recipe_content_5635_item_0.jpg",
            "languageId": null
        },
        {
            "stepNo": 6,
            "content": "把排骨出水10分鐘",
            "imageUrl": "http://pic.daydaycook.com/production/ImageMigration/384x288/recipe_content_5635_item_1.jpg",
            "languageId": null
        },
        {
            "stepNo": 7,
            "content": "將白米，薑片，排骨放入鍋內",
            "imageUrl": "http://pic.daydaycook.com/production/ImageMigration/384x288/recipe_content_5636_item_0.jpg",
            "languageId": null
        },
        {
            "stepNo": 8,
            "content": "加入清水",
            "imageUrl": "http://pic.daydaycook.com/production/ImageMigration/384x288/recipe_content_5636_item_1.jpg",
            "languageId": null
        },
        {
            "stepNo": 9,
            "content": "加入切塊的芋頭繼續煮",
            "imageUrl": "http://pic.daydaycook.com/production/ImageMigration/384x288/recipe_content_5637_item_0.jpg",
            "languageId": null
        },
        {
            "stepNo": 10,
            "content": "加入調味料",
            "imageUrl": "http://pic.daydaycook.com/production/ImageMigration/384x288/recipe_content_5637_item_1.jpg",
            "languageId": null
        },
        {
            "stepNo": 11,
            "content": "灑上蔥花",
            "imageUrl": "http://pic.daydaycook.com/production/ImageMigration/384x288/recipe_content_5638_item_0.jpg",
            "languageId": null
        },
        {
            "stepNo": 12,
            "content": "即成",
            "imageUrl": "http://pic.daydaycook.com/production/ImageMigration/384x288/recipe_content_5638_item_1.jpg",
            "languageId": null
        }
    ],
    "multipleRateUrl": "http://www.daydaycook.com.cn:80/daydaycook/server/recipe/detailVideo.do?id=1353&languageId=2&mainland=2&site=bve",
    "shareUrl": "http://www.daydaycook.com.cn:80/daydaycook/h5/recipe/recipedetail.do?id=1353&languageId=2&mainland=2&ver=2&regionCode=156"
}