{
    "id": 24391,
    "title": "自家製醃酸瓜",
    "description": "",
    "detailsUrl": "",
    "indexUrl": null,
    "imageUrl": "http://pic.daydaycook.com/production/ImageMigration/1000x750/recipe_24391_23691.jpg",
    "clickCount": 1448,
    "shareCount": 0,
    "maketime": "10分鐘",
    "releaseDate": "2014-06-09 00:00:00.0",
    "ingredientImageUrl": null,
    "ingredientImageUrl2": null,
    "ingredientImageUrl3": null,
    "ingredients": [
        {
            "name": "水",
            "cnt": "100",
            "unit": "毫升",
            "type": "0",
            "typeName": null
        },
        {
            "name": "砂糖",
            "cnt": "100",
            "unit": "克",
            "type": "0",
            "typeName": null
        },
        {
            "name": "白蘿蔔",
            "cnt": "100",
            "unit": "克",
            "type": "0",
            "typeName": null
        },
        {
            "name": "白醋",
            "cnt": "100",
            "unit": "毫升",
            "type": "0",
            "typeName": null
        },
        {
            "name": "紅蘿蔔",
            "cnt": "25",
            "unit": "個",
            "type": "0",
            "typeName": null
        }
    ],
    "steps": [
        {
            "stepNo": 1,
            "content": "把白蘿蔔及紅蘿蔔切條",
            "imageUrl": "http://pic.daydaycook.com/production/ImageMigration/384x288/recipe_content_54431_item_0.jpg",
            "languageId": null
        },
        {
            "stepNo": 2,
            "content": "在煲內，混合水及糖至糖溶化，待涼備用。然後，在糖水內倒入白醋，拌勻",
            "imageUrl": "http://pic.daydaycook.com/production/ImageMigration/384x288/recipe_content_54431_item_1.jpg",
            "languageId": null
        },
        {
            "stepNo": 3,
            "content": "將紅蘿蔔及白蘿蔔放入醃料中",
            "imageUrl": "http://pic.daydaycook.com/production/ImageMigration/384x288/recipe_content_54441_item_0.jpg",
            "languageId": null
        },
        {
            "stepNo": 4,
            "content": "醃24小時，亦可存放於雪櫃1個月",
            "imageUrl": "http://pic.daydaycook.com/production/ImageMigration/384x288/recipe_content_54441_item_1.jpg",
            "languageId": null
        }
    ],
    "multipleRateUrl": "",
    "shareUrl": "http://www.daydaycook.com.cn:80/daydaycook/h5/recipe/recipedetail.do?id=24391&languageId=2&mainland=2&ver=2&regionCode=156"
}